wikiframe/__init__.py
wikiframe/cow_say.py
wikiframe/extractor.py
wikiframe/utils.py
wikiframe-0.0.6.dist-info/LICENCE.md
wikiframe-0.0.6.dist-info/METADATA
wikiframe-0.0.6.dist-info/WHEEL
wikiframe-0.0.6.dist-info/top_level.txt
wikiframe-0.0.6.dist-info/RECORD
