Metadata-Version: 2.1
Name: wikiframe
Version: 0.0.6
Summary: Convert all csv files in a folder to a diccionary of dataframe and more
Author: MasamioNakada
Author-email: nakada2130@gmail.com
License: UNKNOWN
Keywords: pandas,read_csv,automated,dataframe,csv,etl,extract
Platform: UNKNOWN
Classifier: Development Status :: 1 - Planning
Classifier: Intended Audience :: Developers
Classifier: Programming Language :: Python :: 3
Classifier: Operating System :: Unix
Classifier: Operating System :: MacOS :: MacOS X
Classifier: Operating System :: Microsoft :: Windows
License-File: LICENCE.md
Requires-Dist: numpy
Requires-Dist: pandas
Requires-Dist: python-dateutil
Requires-Dist: pytz
Requires-Dist: six
Requires-Dist: chardet
